email_summarizer/__init__.py
email_summarizer/classifier.py
email_summarizer/cli.py
email_summarizer/fetcher.py
email_summarizer/parser.py
email_summarizer/summarizer.py
email_summarizer/utils.py
tests/__init__.py
tests/test_classifier.py
tests/test_parser.py
tests/test_summarizer.py
email_summarizer-0.1.0.dist-info/METADATA
email_summarizer-0.1.0.dist-info/WHEEL
email_summarizer-0.1.0.dist-info/entry_points.txt
email_summarizer-0.1.0.dist-info/top_level.txt
email_summarizer-0.1.0.dist-info/RECORD
