Metadata-Version: 2.4
Name: email_summarizer
Version: 0.1.0
Summary: CLI tool to summarize and classify email/LinkedIn threads
Author-email: Rohit Rajesh <your-email@example.com>
License: MIT
Requires-Python: >=3.8
Requires-Dist: openai
Requires-Dist: python-dotenv
Requires-Dist: google-api-python-client
Requires-Dist: google-auth-httplib2
Requires-Dist: google-auth-oauthlib
